pyham/TreeProfile.py
pyham/__init__.py
pyham/abstractgene.py
pyham/genome.py
pyham/ham.py
pyham/iham.py
pyham/mapper.py
pyham/parsers.py
pyham/taxonomy.py
pyham/utils.py
pyham-1.2.0.dist-info/LICENSE.txt
pyham-1.2.0.dist-info/METADATA
pyham-1.2.0.dist-info/WHEEL
pyham-1.2.0.dist-info/top_level.txt
pyham-1.2.0.dist-info/RECORD
