Metadata-Version: 2.1
Name: pyham
Version: 1.2.0
Summary: A tool to analyse Hierarchical Orthologous Groups (HOGs)
Home-page: http://lab.dessimoz.org/ham
Author: Dessimoz Lab - Laboratory of Computational Evolutionary Biology and Genomics
Author-email: adrian.altenhoff@inf.ethz.ch
License: MIT
Keywords: orthology, HOGs, orthoxml
Classifier: Development Status :: 5 - Production/Stable
Classifier: Environment :: Console
Classifier: Intended Audience :: Developers
Classifier: Intended Audience :: Science/Research
Classifier: Topic :: Scientific/Engineering :: Bio-Informatics
Classifier: License :: OSI Approved :: MIT License
Classifier: Programming Language :: Python :: 2
Classifier: Programming Language :: Python :: 2.7
Classifier: Programming Language :: Python :: 3
Classifier: Programming Language :: Python :: 3.5
Classifier: Programming Language :: Python :: 3.6
Classifier: Programming Language :: Python :: 3.7
Classifier: Programming Language :: Python :: 3.8
Classifier: Programming Language :: Python :: 3.9
Classifier: Programming Language :: Python :: 3.10
Classifier: Programming Language :: Python :: 3.11
License-File: LICENSE.txt
Requires-Dist: ete3 >=3.1
Requires-Dist: six
Requires-Dist: lxml
Requires-Dist: future
Requires-Dist: requests
Requires-Dist: tqdm
Requires-Dist: scipy
Provides-Extra: dev
Requires-Dist: nose ; extra == 'dev'
Requires-Dist: sphinx ; extra == 'dev'
Requires-Dist: wheel ; extra == 'dev'
Requires-Dist: twine ; extra == 'dev'
Requires-Dist: fabric ; extra == 'dev'
Requires-Dist: fabric3 ; extra == 'dev'
Provides-Extra: test
Requires-Dist: nose ; extra == 'test'
